lensfunpy-1.18.0.dist-info/RECORD
lensfunpy-1.18.0.dist-info/WHEEL
lensfunpy-1.18.0.dist-info/top_level.txt
lensfunpy-1.18.0.dist-info/METADATA
lensfunpy-1.18.0.dist-info/licenses/LICENSE
lensfunpy/_version.py
lensfunpy/_lensfun.cpython-311-darwin.so
lensfunpy/util.py
lensfunpy/__init__.py
lensfunpy/db_files/compact-canon.xml
lensfunpy/db_files/mil-leica.xml
lensfunpy/db_files/slr-samsung.xml
lensfunpy/db_files/slr-olympus.xml
lensfunpy/db_files/om-system.xml
lensfunpy/db_files/slr-nikon.xml
lensfunpy/db_files/compact-kodak.xml
lensfunpy/db_files/compact-sigma.xml
lensfunpy/db_files/compact-ricoh.xml
lensfunpy/db_files/mil-samyang.xml
lensfunpy/db_files/mil-sony.xml
lensfunpy/db_files/rf-leica.xml
lensfunpy/db_files/slr-vivitar.xml
lensfunpy/db_files/6x6.xml
lensfunpy/db_files/compact-panasonic.xml
lensfunpy/db_files/mil-canon.xml
lensfunpy/db_files/compact-leica.xml
lensfunpy/db_files/compact-konica-minolta.xml
lensfunpy/db_files/slr-zeiss.xml
lensfunpy/db_files/slr-soligor.xml
lensfunpy/db_files/mil-sigma.xml
lensfunpy/db_files/compact-pentax.xml
lensfunpy/db_files/compact-casio.xml
lensfunpy/db_files/slr-konica-minolta.xml
lensfunpy/db_files/actioncams.xml
lensfunpy/db_files/slr-pentax.xml
lensfunpy/db_files/mil-pentax.xml
lensfunpy/db_files/slr-hasselblad.xml
lensfunpy/db_files/mil-nikon.xml
lensfunpy/db_files/compact-fujifilm.xml
lensfunpy/db_files/mil-fujifilm.xml
lensfunpy/db_files/slr-ussr.xml
lensfunpy/db_files/compact-sony.xml
lensfunpy/db_files/contax.xml
lensfunpy/db_files/slr-leica.xml
lensfunpy/db_files/generic.xml
lensfunpy/db_files/mil-panasonic.xml
lensfunpy/db_files/slr-tamron.xml
lensfunpy/db_files/mil-olympus.xml
lensfunpy/db_files/compact-olympus.xml
lensfunpy/db_files/mil-tamron.xml
lensfunpy/db_files/compact-samsung.xml
lensfunpy/db_files/mil-samsung.xml
lensfunpy/db_files/mil-tokina.xml
lensfunpy/db_files/slr-tokina.xml
lensfunpy/db_files/slr-sigma.xml
lensfunpy/db_files/slr-ricoh.xml
lensfunpy/db_files/slr-panasonic.xml
lensfunpy/db_files/mil-zeiss.xml
lensfunpy/db_files/compact-nikon.xml
lensfunpy/db_files/misc.xml
lensfunpy/db_files/slr-sony.xml
