Metadata-Version: 2.4
Name: lensfunpy
Version: 1.18.0
Summary: Lens distortion correction for Python, a wrapper for lensfun
Home-page: https://github.com/letmaik/lensfunpy
Author: Maik Riechert
Classifier: Development Status :: 4 - Beta
Classifier: Intended Audience :: Developers
Classifier: Natural Language :: English
Classifier: License :: OSI Approved :: MIT License
Classifier: Programming Language :: Cython
Classifier: Programming Language :: Python
Classifier: Programming Language :: Python :: 3
Classifier: Operating System :: MacOS
Classifier: Operating System :: Microsoft :: Windows
Classifier: Operating System :: POSIX
Classifier: Operating System :: Unix
Classifier: Topic :: Multimedia :: Graphics
Classifier: Topic :: Software Development :: Libraries
License-File: LICENSE
Requires-Dist: numpy
Dynamic: author
Dynamic: classifier
Dynamic: description
Dynamic: home-page
Dynamic: license-file
Dynamic: requires-dist
Dynamic: summary
